<?xml version="1.0" ?>

<container xmlns="http://symfony.com/schema/dic/services"
    xmlns:xsi="http://www.w3.org/2001/XMLSchema-instance"
    xsi:schemaLocation="http://symfony.com/schema/dic/services http://symfony.com/schema/dic/services/services-1.0.xsd">

    <!--
    <parameters>
        <parameter key="medicheck_user.example.class">Medicheck\UserBundle\Example</parameter>
    </parameters>

    <services>
        <service id="medicheck_user.example" class="%medicheck_user.example.class%">
            <argument type="service" id="service_id" />
            <argument>plain_value</argument>
            <argument>%parameter_name%</argument>
        </service>
    </services>
    -->


    <!-- parameters>
        <parameter key="kolor.user_manager.class">Kolor\UserBundle\Model\UserManager</parameter>
        <parameter key="kolor_user.factory.user.class">Kolor\UserBundle\Entity\UserFactory</parameter>
    </parameters>

    <services>
        <service id="kolor_user.factory.user" class="%kolor_user.factory.user.class%" />

        <service id="kolor.user_manager" class="%kolor.user_manager.class%">
            <argument type="service" id="security.encoder_factory" />
            <argument type="service" id="kolor_user.repository.user" />
            <argument>%time_validity%</argument>
            <tag name="monolog.logger" channel="kolor.user" />
        </service>
    </services -->
</container>
